make_parser.py
make_parser-0.1.2.dist-info/LICENSE
make_parser-0.1.2.dist-info/METADATA
make_parser-0.1.2.dist-info/WHEEL
make_parser-0.1.2.dist-info/entry_points.txt
make_parser-0.1.2.dist-info/top_level.txt
make_parser-0.1.2.dist-info/RECORD
